odoo10_addon_account_payment_mode_auto_reconcile-10.0.1.0.0.99.dev8-py3.8-nspkg.pth
odoo/addons/account_payment_mode_auto_reconcile/README.rst
odoo/addons/account_payment_mode_auto_reconcile/__init__.py
odoo/addons/account_payment_mode_auto_reconcile/__manifest__.py
odoo/addons/account_payment_mode_auto_reconcile/demo/account_payment_mode.xml
odoo/addons/account_payment_mode_auto_reconcile/i18n/account_payment_mode_auto_reconcile.pot
odoo/addons/account_payment_mode_auto_reconcile/models/__init__.py
odoo/addons/account_payment_mode_auto_reconcile/models/account_invoice.py
odoo/addons/account_payment_mode_auto_reconcile/models/account_partial_reconcile.py
odoo/addons/account_payment_mode_auto_reconcile/models/account_payment_mode.py
odoo/addons/account_payment_mode_auto_reconcile/readme/CONTRIBUTORS.rst
odoo/addons/account_payment_mode_auto_reconcile/readme/DESCRIPTION.rst
odoo/addons/account_payment_mode_auto_reconcile/static/description/icon.png
odoo/addons/account_payment_mode_auto_reconcile/static/description/index.html
odoo/addons/account_payment_mode_auto_reconcile/tests/__init__.py
odoo/addons/account_payment_mode_auto_reconcile/tests/test_partner_auto_reconcile.py
odoo/addons/account_payment_mode_auto_reconcile/views/account_invoice.xml
odoo/addons/account_payment_mode_auto_reconcile/views/account_payment_mode.xml
odoo10_addon_account_payment_mode_auto_reconcile-10.0.1.0.0.99.dev8.dist-info/METADATA
odoo10_addon_account_payment_mode_auto_reconcile-10.0.1.0.0.99.dev8.dist-info/WHEEL
odoo10_addon_account_payment_mode_auto_reconcile-10.0.1.0.0.99.dev8.dist-info/namespace_packages.txt
odoo10_addon_account_payment_mode_auto_reconcile-10.0.1.0.0.99.dev8.dist-info/top_level.txt
odoo10_addon_account_payment_mode_auto_reconcile-10.0.1.0.0.99.dev8.dist-info/RECORD
